WeiLanZouCloud/__init__.py
WeiLanZouCloud/api/__init__.py
WeiLanZouCloud/api/core.py
WeiLanZouCloud/api/models.py
WeiLanZouCloud/api/types.py
WeiLanZouCloud/api/utils.py
weilanzou_api-0.0.2.dist-info/LICENSE
weilanzou_api-0.0.2.dist-info/METADATA
weilanzou_api-0.0.2.dist-info/WHEEL
weilanzou_api-0.0.2.dist-info/top_level.txt
weilanzou_api-0.0.2.dist-info/RECORD
