Metadata-Version: 2.1
Name: weilanzou-api
Version: 0.0.2
Summary: Fixed the old version of LanZouCloud API.
Home-page: https://github.com/acloudtwei/WeiLanZouCloud-API
Author: Acloudtwei
Author-email: 1559295172@qq.com
License: UNKNOWN
Platform: UNKNOWN
Classifier: Programming Language :: Python :: 3
Classifier: Operating System :: OS Independent
License-File: LICENSE
Requires-Dist: requests
Requires-Dist: requests-toolbelt
Requires-Dist: fake-useragent (==0.1.11)
